core/__init__.py
core/main.py
documents_analysis_engine-0.0.1.dist-info/LICENSE
documents_analysis_engine-0.0.1.dist-info/METADATA
documents_analysis_engine-0.0.1.dist-info/WHEEL
documents_analysis_engine-0.0.1.dist-info/top_level.txt
documents_analysis_engine-0.0.1.dist-info/RECORD
