Metadata-Version: 2.1
Name: documents-analysis-engine
Version: 0.0.1
Summary: documents analysis engine
Home-page: https://github.com/seong-min-a/documents-analysis-engine
Author: seong-min-a
Author-email: seong.min.ahn.x@gmail.com
Project-URL: Bug Tracker, https://github.com/seong-min-a/documents-analysis-engine/issues
Classifier: Programming Language :: Python :: 3
Classifier: License :: OSI Approved :: MIT License
Classifier: Operating System :: OS Independent
Requires-Python: >=3.8
License-File: LICENSE
